pimporter/__init__.py
pimporter/__main__.py
pimporter/_analyze_file-splitvorschlag.py
pimporter/main.py
pimporter-0.1.12.dist-info/METADATA
pimporter-0.1.12.dist-info/WHEEL
pimporter-0.1.12.dist-info/entry_points.txt
pimporter-0.1.12.dist-info/top_level.txt
pimporter-0.1.12.dist-info/RECORD
