Metadata-Version: 2.4
Name: pimporter
Version: 0.1.12
Summary: Checks for conflicting, unused or duplicate import aliases
Author: MWB
License-Expression: MIT
Requires-Python: >=3.8
Requires-Dist: colorama
